README.rst
setup.py
tornado_alf.egg-info/PKG-INFO
tornado_alf.egg-info/SOURCES.txt
tornado_alf.egg-info/dependency_links.txt
tornado_alf.egg-info/requires.txt
tornado_alf.egg-info/top_level.txt
tornadoalf/__init__.py
tornadoalf/client.py
tornadoalf/manager.py
tornadoalf/token.py