Metadata-Version: 2.1
Name: tornado-alf
Version: 0.5.0rc1
Summary: OAuth Client For Tornado
Home-page: https://github.com/globocom/tornado-alf
Author: Globo.com
Author-email: entretenimento1@corp.globo.com
License: MIT
Keywords: oauth client client_credentials tornado
Platform: UNKNOWN
Classifier: Development Status :: 4 - Beta
Classifier: Intended Audience :: Developers
Classifier: License :: OSI Approved :: MIT License
Classifier: Natural Language :: English
Classifier: Operating System :: MacOS
Classifier: Operating System :: POSIX
Classifier: Operating System :: Unix
Classifier: Operating System :: OS Independent
Classifier: Programming Language :: Python :: 2.7
Classifier: Programming Language :: Python :: 3.4
Provides-Extra: tests
